deutschland/pflanzenschutzmittelzulassung/__init__.py
deutschland/pflanzenschutzmittelzulassung/api/__init__.py
deutschland/pflanzenschutzmittelzulassung/api/default_api.py
deutschland/pflanzenschutzmittelzulassung/api_client.py
deutschland/pflanzenschutzmittelzulassung/apis/__init__.py
deutschland/pflanzenschutzmittelzulassung/configuration.py
deutschland/pflanzenschutzmittelzulassung/exceptions.py
deutschland/pflanzenschutzmittelzulassung/model/__init__.py
deutschland/pflanzenschutzmittelzulassung/model/date.py
deutschland/pflanzenschutzmittelzulassung/model/inline_response200.py
deutschland/pflanzenschutzmittelzulassung/model/inline_response2001.py
deutschland/pflanzenschutzmittelzulassung/model/inline_response20010.py
deutschland/pflanzenschutzmittelzulassung/model/inline_response20010_items.py
deutschland/pflanzenschutzmittelzulassung/model/inline_response20011.py
deutschland/pflanzenschutzmittelzulassung/model/inline_response20011_items.py
deutschland/pflanzenschutzmittelzulassung/model/inline_response20012.py
deutschland/pflanzenschutzmittelzulassung/model/inline_response20012_items.py
deutschland/pflanzenschutzmittelzulassung/model/inline_response20013.py
deutschland/pflanzenschutzmittelzulassung/model/inline_response20013_items.py
deutschland/pflanzenschutzmittelzulassung/model/inline_response20014.py
deutschland/pflanzenschutzmittelzulassung/model/inline_response20014_items.py
deutschland/pflanzenschutzmittelzulassung/model/inline_response20015.py
deutschland/pflanzenschutzmittelzulassung/model/inline_response20015_items.py
deutschland/pflanzenschutzmittelzulassung/model/inline_response20016.py
deutschland/pflanzenschutzmittelzulassung/model/inline_response20016_items.py
deutschland/pflanzenschutzmittelzulassung/model/inline_response20017.py
deutschland/pflanzenschutzmittelzulassung/model/inline_response20017_items.py
deutschland/pflanzenschutzmittelzulassung/model/inline_response20018.py
de_pflanzenschutzmittelzulassung-0.1.0.dist-info/WHEEL
de_pflanzenschutzmittelzulassung-0.1.0.dist-info/METADATA
de_pflanzenschutzmittelzulassung-0.1.0.dist-info/RECORD
